numpy_utils.py
tests/__init__.py
tests/test.py
numpy_utils-0.1.5.1.dist-info/METADATA
numpy_utils-0.1.5.1.dist-info/WHEEL
numpy_utils-0.1.5.1.dist-info/top_level.txt
numpy_utils-0.1.5.1.dist-info/RECORD
