Metadata-Version: 2.1
Name: numpy-utils
Version: 0.1.5.1
Summary: NumPy utilities.
Home-page: https://github.com/deluccial/numpy_utils.git
Author: Luke DeLuccia
Author-email: deluccial@gmail.com
License: UNKNOWN
Platform: UNKNOWN
Classifier: Programming Language :: Python :: 3.5
Classifier: Programming Language :: Python :: 3.6
Classifier: Programming Language :: Python :: 3.7
Classifier: License :: OSI Approved :: MIT License
Classifier: Operating System :: OS Independent
Requires-Dist: numpy
